ngn/__init__.py
ngn/main.py
ngn/tk_table.py
ngn/aws/__init__.py
ngn/aws/actions old 01.py
ngn/aws/actions old 02.py
ngn/aws/actions.py
ngn/aws/assign_tags02.py
ngn/aws/call_price.py
ngn/aws/costmonth02.py
ngn/aws/costmonth03.py
ngn/aws/costmonth04.py
ngn/aws/costmonth05.py
ngn/aws/data.py
ngn/aws/mult01.py
ngn/aws/mult02.py
ngn/aws/mult03.py
ngn/aws/mult04.py
ngn/aws/mult05.py
ngn/aws/prices00.py
ngn/aws/prices01.py
ngn/aws/prices02.py
ngn/aws/prulists.py
ngn/aws/resource00.py
ngn/aws/resource01.py
ngn/aws/types01.py
ngn/config/__init__.py
ngn/config/base_dict.py
ngn/config/classes.py
ngn/config/config.py
ngn/do/__init__.py
ngn/do/actions.py
ngn/do/actions_old01.py
ngn/do/data.py
ngn/het/__init__.py
ngn/het/actions.py
ngn/het/data.py
ngn/lin/__init__.py
ngn/lin/actions.py
ngn/lin/data.py
ngn/lin/lin_pru.py
costngn_cli-0.0.18.dist-info/LICENSE.txt
costngn_cli-0.0.18.dist-info/METADATA
costngn_cli-0.0.18.dist-info/WHEEL
costngn_cli-0.0.18.dist-info/entry_points.txt
costngn_cli-0.0.18.dist-info/top_level.txt
costngn_cli-0.0.18.dist-info/RECORD
